streamlit_cardv2/__init__.py
streamlit_cardv2/frontend/build/asset-manifest.json
streamlit_cardv2/frontend/build/bootstrap.min.css
streamlit_cardv2/frontend/build/bootstrap.min.css.map
streamlit_cardv2/frontend/build/index.html
streamlit_cardv2/frontend/build/precache-manifest.3d1d75a54aa1cab9d03088d8f3e15079.js
streamlit_cardv2/frontend/build/service-worker.js
streamlit_cardv2/frontend/build/static/js/2.a5b5137d.chunk.js
streamlit_cardv2/frontend/build/static/js/2.a5b5137d.chunk.js.map
streamlit_cardv2/frontend/build/static/js/main.78999827.chunk.js
streamlit_cardv2/frontend/build/static/js/main.78999827.chunk.js.map
streamlit_cardv2/frontend/build/static/js/runtime~main.d653cc00.js
streamlit_cardv2/frontend/build/static/js/runtime~main.d653cc00.js.map
streamlit_cardv2-0.0.1rc2.dist-info/LICENSE
streamlit_cardv2-0.0.1rc2.dist-info/METADATA
streamlit_cardv2-0.0.1rc2.dist-info/WHEEL
streamlit_cardv2-0.0.1rc2.dist-info/top_level.txt
streamlit_cardv2-0.0.1rc2.dist-info/RECORD
