Metadata-Version: 2.1
Name: streamlit-cardv2
Version: 0.0.1rc2
Summary: A streamlit component, to make UI cards
Home-page: https://github.com/hortojac/st-card
Author: hortojac
Author-email: hortonjacob250@gmail.com
Keywords: card streamlit streamlit-component
Classifier: Programming Language :: Python :: 3
Classifier: Operating System :: OS Independent
Requires-Python: >=3.8
License-File: LICENSE
Requires-Dist: streamlit (>=0.63)
